pyprycd/__init__.py
pyprycd/pyprycd.py
pyprycd/data/__init__.py
pyprycd/data/county_fips_master.csv
pyprycd-0.1.13.dist-info/LICENSE
pyprycd-0.1.13.dist-info/METADATA
pyprycd-0.1.13.dist-info/WHEEL
pyprycd-0.1.13.dist-info/top_level.txt
pyprycd-0.1.13.dist-info/RECORD
