Metadata-Version: 2.1
Name: pyprycd
Version: 0.1.13
Summary: An unofficial Python Client for the PRYCD API for Real Estate Analysis.
Author-email: "Charles S. Givre" <charles@geniza.ai>
License: MIT License
Project-URL: Repository, https://github.com/geniza-ai/pyprycd
Project-URL: Issues, https://github.com/geniza-ai/pyprycd/issues
Keywords: Real Estate,data,analysis
Classifier: Development Status :: 4 - Beta
Classifier: Intended Audience :: Developers
Classifier: License :: OSI Approved :: MIT License
Classifier: Programming Language :: Python :: 3.11
Classifier: Programming Language :: Python :: 3.10
Requires-Python: >=3.10
License-File: LICENSE
Requires-Dist: dateparser
Requires-Dist: requests
Requires-Dist: pyarrow
Requires-Dist: pandas
